<?xml version="1.0" encoding="utf-8"?>
<Deployment xmlns="http://schemas.microsoft.com/windowsphone/2012/deployment" AppPlatformVersion="8.0">
  <DefaultLanguage xmlns="" code="de-DE" />
  <App xmlns="" ProductID="{2c137d8b-d5d3-4d89-8445-535e7c3d4a32}" Title="CWS Informant Lehrer BETA" RuntimeType="Silverlight" Version="1.0.0.0" Genre="apps.normal" Author="vplan author" Description="Sample description" Publisher="vplan" PublisherID="{1f789041-e0f7-4b23-b332-981dea7fd6da}">
    <IconPath IsRelative="true" IsResource="false">Assets\ApplicationIcon.png</IconPath>
    <Capabilities>
      <Capability Name="ID_CAP_NETWORKING" />
    </Capabilities>
    <Tasks>
      <DefaultTask Name="_default" NavigationPage="MainPage.xaml" />
      <ExtendedTask Name="DataUpdateTask">
        <BackgroundServiceAgent Specifier="ScheduledTaskAgent" Name="DataUpdate" Source="DataUpdate" Type="DataUpdate.ScheduledAgent" />
      </ExtendedTask>
    </Tasks>
    <Tokens>
      <PrimaryToken TokenID="vplanToken" TaskName="_default">
        <TemplateIconic>
          <SmallImageURI IsRelative="true" IsResource="false">Assets\Tiles\IconicTileSmall.png</SmallImageURI>
          <Count>0</Count>
          <IconImageURI IsRelative="true" IsResource="false">Assets\Tiles\IconicTileMediumLarge.png</IconImageURI>
          <Title>CWS Informant Lehrer BETA</Title>
          <Message>
          </Message>
          <BackgroundColor>
          </BackgroundColor>
          <HasLarge>True</HasLarge>
          <LargeContent1>
          </LargeContent1>
          <LargeContent2>
          </LargeContent2>
          <LargeContent3>
          </LargeContent3>
          <DeviceLockImageURI IsRelative="true" IsResource="false">Assets\LockImage.png</DeviceLockImageURI>
        </TemplateIconic>
      </PrimaryToken>
    </Tokens>
    <Extensions>
      <Extension ExtensionName="LockScreen_Notification_IconCount" ConsumerID="{111DFF24-AA15-4A96-8006-2BFF8122084F}" TaskID="_default" />
    </Extensions>
    <ScreenResolutions>
      <ScreenResolution Name="ID_RESOLUTION_WVGA" />
      <ScreenResolution Name="ID_RESOLUTION_WXGA" />
      <ScreenResolution Name="ID_RESOLUTION_HD720P" />
    </ScreenResolutions>
  </App>
</Deployment>